ashrio/__init__.py
ashrio/button/__init__.py
ashrio/button/button.py
ashrio/button/defaults.py
ashrio/button/example/__init__.py
ashrio/button/example/example.py
ashrio/button/styles.py
ashrio/card/__init__.py
ashrio/card/card.py
ashrio/events/__init__.py
ashrio/events/core.py
ashrio/events/statefulbutton.py
ashrio/events/statefultext.py
ashrio/example.py
ashrio/grid/__init__.py
ashrio/grid/core.py
ashrio/modal/__init__.py
ashrio/modal/modal.py
ashrio/output.html
ashrio/tailwind/__init__.py
ashrio/tailwind/twstyles.py
ashrio/text/__init__.py
ashrio/text/example/example.py
ashrio/text/styles.py
ashrio/text/text.py
ashrio/utils/__init__.py
ashrio/utils/core.py
ashrio-0.1.0.dist-info/LICENSE
ashrio-0.1.0.dist-info/METADATA
ashrio-0.1.0.dist-info/WHEEL
ashrio-0.1.0.dist-info/RECORD
