Metadata-Version: 2.1
Name: ashrio
Version: 0.1.0
Summary: Frontend web development, in python, for python.
License: MIT
Author: Asher
Requires-Python: >=3.12,<4.0
Classifier: License :: OSI Approved :: MIT License
Classifier: Programming Language :: Python :: 3
Classifier: Programming Language :: Python :: 3.12
Requires-Dist: pydantic (>=2.6.1,<3.0.0)
